typedstream/__init__.py
typedstream/__main__.py
typedstream/advanced_repr.py
typedstream/archiving.py
typedstream/encodings.py
typedstream/old_binary_plist.py
typedstream/stream.py
typedstream/types/__init__.py
typedstream/types/_common.py
typedstream/types/appkit.py
typedstream/types/core_graphics.py
typedstream/types/foundation.py
typedstream/types/nextstep.py
pytypedstream-0.1.0.dist-info/COPYING.LESSER.txt
pytypedstream-0.1.0.dist-info/COPYING.txt
pytypedstream-0.1.0.dist-info/METADATA
pytypedstream-0.1.0.dist-info/WHEEL
pytypedstream-0.1.0.dist-info/entry_points.txt
pytypedstream-0.1.0.dist-info/top_level.txt
pytypedstream-0.1.0.dist-info/RECORD
