Metadata-Version: 2.1
Name: pytypedstream
Version: 0.1.0
Summary: A pure Python, cross-platform library/tool for reading Mac OS X and NeXTSTEP typedstream files
Home-page: https://github.com/dgelessus/python-typedstream
Author: dgelessus
License: LGPL-3.0-or-later
Keywords: typedstream,streamtyped,nsarchiver,nsunarchiver,nxtypedstream,mac,macosx,osx,macos,nextstep
Classifier: Development Status :: 4 - Beta
Classifier: Intended Audience :: Developers
Classifier: Topic :: Software Development :: Disassemblers
Classifier: Topic :: System
Classifier: Topic :: Utilities
Classifier: License :: OSI Approved :: GNU Lesser General Public License v3 or later (LGPLv3+)
Classifier: Operating System :: MacOS :: MacOS X
Classifier: Operating System :: OS Independent
Classifier: Programming Language :: Python
Classifier: Programming Language :: Python :: 3
Classifier: Programming Language :: Python :: 3 :: Only
Classifier: Programming Language :: Python :: 3.6
Classifier: Programming Language :: Python :: 3.7
Classifier: Programming Language :: Python :: 3.8
Classifier: Programming Language :: Python :: 3.9
Classifier: Programming Language :: Python :: 3.10
Classifier: Programming Language :: Python :: 3.11
Requires-Python: >=3.6
License-File: COPYING.txt
License-File: COPYING.LESSER.txt
